python_camunda_sdk/__init__.py
python_camunda_sdk/connectors/__init__.py
python_camunda_sdk/connectors/config.py
python_camunda_sdk/connectors/connector.py
python_camunda_sdk/connectors/inbound.py
python_camunda_sdk/connectors/outbound.py
python_camunda_sdk/runtime/__init__.py
python_camunda_sdk/runtime/config.py
python_camunda_sdk/runtime/runtime.py
python_camunda_sdk/templates/__init__.py
python_camunda_sdk/templates/cli.py
python_camunda_sdk/templates/template.py
python_camunda_sdk/types.py
python_camunda_sdk-1.0.1.dist-info/LICENSE
python_camunda_sdk-1.0.1.dist-info/METADATA
python_camunda_sdk-1.0.1.dist-info/WHEEL
python_camunda_sdk-1.0.1.dist-info/entry_points.txt
python_camunda_sdk-1.0.1.dist-info/RECORD
